captcha_solver/__init__.py
captcha_solver/__version__.py
captcha_solver/check_captcha.py
captcha_solver/lib/__init__.py
captcha_solver/lib/common.onnx
captcha_solver/lib/common_det.onnx
captcha_solver/lib/common_old.onnx
captcha_solver/read_captcha.py
mh_captcha_solver-0.1.0.dist-info/METADATA
mh_captcha_solver-0.1.0.dist-info/WHEEL
mh_captcha_solver-0.1.0.dist-info/RECORD
