Metadata-Version: 2.1
Name: mh_captcha_solver
Version: 0.1.0
Requires-Python: <3.12,>=3.8
Requires-Dist: opencv-python-headless==4.8.0.76
Requires-Dist: numpy==1.24.4
Requires-Dist: onnxruntime==1.15.1
Requires-Dist: pillow==9.5.0
